pytrend_cli/__init__.py
pytrend_cli/pytrend.py
pytrend_cli-1.19.dist-info/DESCRIPTION.rst
pytrend_cli-1.19.dist-info/METADATA
pytrend_cli-1.19.dist-info/RECORD
pytrend_cli-1.19.dist-info/WHEEL
pytrend_cli-1.19.dist-info/entry_points.txt
pytrend_cli-1.19.dist-info/metadata.json
pytrend_cli-1.19.dist-info/top_level.txt
