Metadata-Version: 2.0
Name: pytrend-cli
Version: 1.19
Summary: Get trending GitHub repositories daily/weekly/monthly and by language
Home-page: https://github.com/evyatarmeged/pytrend-cli
Author: Evyatar Meged
Author-email: evyatarmeged@gmail.com
License: MIT
Keywords: GitHub,trending,repositories,developers,scraping
Platform: UNKNOWN
Requires-Dist: beautifulsoup4
Requires-Dist: requests
Requires-Dist: lxml
